vector2d.py
vector2d.py-1.2.3.dist-info/LICENSE
vector2d.py-1.2.3.dist-info/METADATA
vector2d.py-1.2.3.dist-info/WHEEL
vector2d.py-1.2.3.dist-info/top_level.txt
vector2d.py-1.2.3.dist-info/RECORD
